camphr_pattern_search/VERSION.py
camphr_pattern_search/__init__.py
camphr_pattern_search/pattern_search.py
camphr_pattern_search-0.1.0.dist-info/WHEEL
camphr_pattern_search-0.1.0.dist-info/METADATA
camphr_pattern_search-0.1.0.dist-info/RECORD
